odoo/addons/datev_export_dtvf/README.rst
odoo/addons/datev_export_dtvf/__init__.py
odoo/addons/datev_export_dtvf/__manifest__.py
odoo/addons/datev_export_dtvf/datev.py
odoo/addons/datev_export_dtvf/data/ir_cron.xml
odoo/addons/datev_export_dtvf/data/mail_template.xml
odoo/addons/datev_export_dtvf/i18n/.empty
odoo/addons/datev_export_dtvf/i18n/datev_export_dtvf.pot
odoo/addons/datev_export_dtvf/models/__init__.py
odoo/addons/datev_export_dtvf/models/account_account.py
odoo/addons/datev_export_dtvf/models/datev_export_dtvf.py
odoo/addons/datev_export_dtvf/models/res_partner.py
odoo/addons/datev_export_dtvf/readme/CONFIGURE.rst
odoo/addons/datev_export_dtvf/readme/CONTRIBUTORS.rst
odoo/addons/datev_export_dtvf/readme/DESCRIPTION.rst
odoo/addons/datev_export_dtvf/readme/ROADMAP.rst
odoo/addons/datev_export_dtvf/readme/USAGE.rst
odoo/addons/datev_export_dtvf/readme/newsfragments/.gitkeep
odoo/addons/datev_export_dtvf/security/ir.model.access.csv
odoo/addons/datev_export_dtvf/static/description/icon.png
odoo/addons/datev_export_dtvf/static/description/index.html
odoo/addons/datev_export_dtvf/tests/__init__.py
odoo/addons/datev_export_dtvf/tests/test_datev_export_dtvf.py
odoo/addons/datev_export_dtvf/views/account_account.xml
odoo/addons/datev_export_dtvf/views/datev_export_dtvf.xml
odoo/addons/datev_export_dtvf/views/res_partner.xml
odoo_addon_datev_export_dtvf-15.0.2.0.0.dist-info/METADATA
odoo_addon_datev_export_dtvf-15.0.2.0.0.dist-info/WHEEL
odoo_addon_datev_export_dtvf-15.0.2.0.0.dist-info/top_level.txt
odoo_addon_datev_export_dtvf-15.0.2.0.0.dist-info/RECORD
