Metadata-Version: 2.1
Name: odoo-addon-datev_export_dtvf
Version: 15.0.2.0.0
Summary: Export Data for DATEV (dtvf)
Home-page: https://github.com/OCA/l10n-germany
Author: Hunki Enterprises BV, Odoo Community Association (OCA)
Author-email: support@odoo-community.org
License: AGPL-3
Classifier: Programming Language :: Python
Classifier: Framework :: Odoo
Classifier: Framework :: Odoo :: 15.0
Classifier: License :: OSI Approved :: GNU Affero General Public License v3
Classifier: Development Status :: 4 - Beta
Requires-Python: >=3.8
Requires-Dist: odoo-addon-date-range<15.1dev,>=15.0dev
Requires-Dist: odoo-addon-datev-export<15.1dev,>=15.0dev
Requires-Dist: odoo<15.1dev,>=15.0a
